{
	"info": {
		"_postman_id": "cf1b6fcb-b024-4a8a-b99e-525c21b338d8",
		"name": "Desafio-Pet",
		"schema": "https://schema.getpostman.com/json/collection/v2.1.0/collection.json",
		"_exporter_id": "21044493"
	},
	"item": [
		{
			"name": "Cliente",
			"item": [
				{
					"name": "GET Clientes",
					"request": {
						"auth": {
							"type": "bearer",
							"bearer": [
								{
									"key": "token",
									"value": "eyJ0eXAiOiJKV1QiLCJhbGciOiJIUzI1NiJ9.eyJzdWIiOiIyIiwiaXNzIjoiUHJvZ3JhbWFTVEFSVEVSIiwiZXhwIjoxNjU5MDM1NzE5fQ.BUcnjzUcTuek60ReRsnKh0WioYu-uguzqnqBfg0SOtc",
									"type": "string"
								}
							]
						},
						"method": "GET",
						"header": [],
						"url": {
							"raw": "{{URL_API}}/clientes",
							"host": [
								"{{URL_API}}"
							],
							"path": [
								"clientes"
							]
						}
					},
					"response": []
				},
				{
					"name": "Salvar Cliente",
					"request": {
						"auth": {
							"type": "bearer",
							"bearer": [
								{
									"key": "token",
									"value": "eyJ0eXAiOiJKV1QiLCJhbGciOiJIUzI1NiJ9.eyJzdWIiOiIyIiwiaXNzIjoiUHJvZ3JhbWFTVEFSVEVSIiwiZXhwIjoxNjU5MDM1NzE5fQ.BUcnjzUcTuek60ReRsnKh0WioYu-uguzqnqBfg0SOtc",
									"type": "string"
								}
							]
						},
						"method": "POST",
						"header": [],
						"body": {
							"mode": "raw",
							"raw": "{\r\n    \"nome\" : \"Guilherme\",\r\n    \"email\" : \"luiz@gft.com\",\r\n    \"telefone\" : \"81999999999\",\r\n    \"cpf\" : \"11111111111\",\r\n    \"endereco\" : {\r\n        \"logradouro\" : \"Rua B\",\r\n        \"numero\" : \"1234\",\r\n        \"complemento\" : \"\",\r\n        \"cep\" : \"11111111\"\r\n    },\r\n    \"cachorros\" : [\r\n        {\r\n            \"nome\" : \"cachorro C\",\r\n            \"racaId\" : 1,\r\n            \"idade\" : 3,\r\n            \"peso\" : 22.3,\r\n            \"altura\" : 14.6,\r\n            \"largura\" : 6.1\r\n        },\r\n        {\r\n            \"nome\" : \"cachorro D\",\r\n            \"racaId\" : 8,\r\n            \"idade\" : 5,\r\n            \"peso\" : 17.3,\r\n            \"altura\" : 12.6,\r\n            \"largura\" : 5.1\r\n        }\r\n    ]\r\n}",
							"options": {
								"raw": {
									"language": "json"
								}
							}
						},
						"url": {
							"raw": "{{URL_API}}/clientes",
							"host": [
								"{{URL_API}}"
							],
							"path": [
								"clientes"
							]
						}
					},
					"response": []
				},
				{
					"name": "Buscar por ID",
					"request": {
						"auth": {
							"type": "bearer",
							"bearer": [
								{
									"key": "token",
									"value": "eyJ0eXAiOiJKV1QiLCJhbGciOiJIUzI1NiJ9.eyJzdWIiOiIyIiwiaXNzIjoiUHJvZ3JhbWFTVEFSVEVSIiwiZXhwIjoxNjU5MDM1NzE5fQ.BUcnjzUcTuek60ReRsnKh0WioYu-uguzqnqBfg0SOtc",
									"type": "string"
								}
							]
						},
						"method": "GET",
						"header": [],
						"url": {
							"raw": "{{URL_API}}/clientes/4",
							"host": [
								"{{URL_API}}"
							],
							"path": [
								"clientes",
								"4"
							]
						}
					},
					"response": []
				},
				{
					"name": "Atualiza Cliente",
					"request": {
						"auth": {
							"type": "bearer",
							"bearer": [
								{
									"key": "token",
									"value": "eyJ0eXAiOiJKV1QiLCJhbGciOiJIUzI1NiJ9.eyJzdWIiOiIyIiwiaXNzIjoiUHJvZ3JhbWFTVEFSVEVSIiwiZXhwIjoxNjU5MDM1NzE5fQ.BUcnjzUcTuek60ReRsnKh0WioYu-uguzqnqBfg0SOtc",
									"type": "string"
								}
							]
						},
						"method": "PUT",
						"header": [],
						"body": {
							"mode": "raw",
							"raw": "{\r\n    \"nome\" : \"Guilherme atualizado\",\r\n    \"email\" : \"luiz@gft.com\",\r\n    \"telefone\" : \"81999999999\",\r\n    \"cpf\" : \"11111111111\",\r\n    \"endereco\" : {\r\n        \"logradouro\" : \"Rua B\",\r\n        \"numero\" : \"1234\",\r\n        \"complemento\" : \"\",\r\n        \"cep\" : \"11111111\"\r\n    },\r\n    \"cachorros\" : [\r\n        {\r\n            \"nome\" : \"inui\",\r\n            \"racaId\" : 1,\r\n            \"idade\" : 3,\r\n            \"peso\" : 22.3,\r\n            \"altura\" : 14.6,\r\n            \"largura\" : 6.1\r\n        },\r\n        {\r\n            \"nome\" : \"dog\",\r\n            \"racaId\" : 8,\r\n            \"idade\" : 1,\r\n            \"peso\" : 9.3,\r\n            \"altura\" : 10.6,\r\n            \"largura\" : 3.1\r\n        }\r\n    ]\r\n}",
							"options": {
								"raw": {
									"language": "json"
								}
							}
						},
						"url": {
							"raw": "{{URL_API}}/clientes/4",
							"host": [
								"{{URL_API}}"
							],
							"path": [
								"clientes",
								"4"
							]
						}
					},
					"response": []
				},
				{
					"name": "Excluir Cliente",
					"request": {
						"auth": {
							"type": "bearer",
							"bearer": [
								{
									"key": "token",
									"value": "eyJ0eXAiOiJKV1QiLCJhbGciOiJIUzI1NiJ9.eyJzdWIiOiIyIiwiaXNzIjoiUHJvZ3JhbWFTVEFSVEVSIiwiZXhwIjoxNjU5MTA4NTk4fQ.KxCC1BpzgIAj2djml6pfWn1syKe66ofU94CW-HYlmFg",
									"type": "string"
								}
							]
						},
						"method": "DELETE",
						"header": [],
						"url": {
							"raw": "{{URL_API}}/clientes/5",
							"host": [
								"{{URL_API}}"
							],
							"path": [
								"clientes",
								"5"
							]
						}
					},
					"response": []
				}
			]
		},
		{
			"name": "Cachorro",
			"item": [
				{
					"name": "Buscar Cachorros",
					"request": {
						"auth": {
							"type": "bearer",
							"bearer": [
								{
									"key": "token",
									"value": "eyJ0eXAiOiJKV1QiLCJhbGciOiJIUzI1NiJ9.eyJzdWIiOiIyIiwiaXNzIjoiUHJvZ3JhbWFTVEFSVEVSIiwiZXhwIjoxNjU5MDM1NzE5fQ.BUcnjzUcTuek60ReRsnKh0WioYu-uguzqnqBfg0SOtc",
									"type": "string"
								}
							]
						},
						"method": "GET",
						"header": [],
						"url": {
							"raw": "{{URL_API}}/cachorros",
							"host": [
								"{{URL_API}}"
							],
							"path": [
								"cachorros"
							]
						}
					},
					"response": []
				},
				{
					"name": "Buscar Cachorro por ID",
					"request": {
						"auth": {
							"type": "bearer",
							"bearer": [
								{
									"key": "token",
									"value": "eyJ0eXAiOiJKV1QiLCJhbGciOiJIUzI1NiJ9.eyJzdWIiOiIyIiwiaXNzIjoiUHJvZ3JhbWFTVEFSVEVSIiwiZXhwIjoxNjU5MDM1NzE5fQ.BUcnjzUcTuek60ReRsnKh0WioYu-uguzqnqBfg0SOtc",
									"type": "string"
								}
							]
						},
						"method": "GET",
						"header": [],
						"url": {
							"raw": "{{URL_API}}/cachorros/1",
							"host": [
								"{{URL_API}}"
							],
							"path": [
								"cachorros",
								"1"
							]
						}
					},
					"response": []
				},
				{
					"name": "Salvar Cachorro",
					"request": {
						"auth": {
							"type": "bearer",
							"bearer": [
								{
									"key": "token",
									"value": "eyJ0eXAiOiJKV1QiLCJhbGciOiJIUzI1NiJ9.eyJzdWIiOiIyIiwiaXNzIjoiUHJvZ3JhbWFTVEFSVEVSIiwiZXhwIjoxNjU5MDM1NzE5fQ.BUcnjzUcTuek60ReRsnKh0WioYu-uguzqnqBfg0SOtc",
									"type": "string"
								}
							]
						},
						"method": "POST",
						"header": [],
						"body": {
							"mode": "raw",
							"raw": "{\r\n    \"nome\" : \"Inui\",\r\n    \"racaId\" : 8,\r\n    \"idade\" : 3,\r\n    \"peso\" : 22.3,\r\n    \"altura\" : 14.6,\r\n    \"largura\" : 6.1,\r\n    \"clienteId\" : 1\r\n}",
							"options": {
								"raw": {
									"language": "json"
								}
							}
						},
						"url": {
							"raw": "{{URL_API}}/cachorros",
							"host": [
								"{{URL_API}}"
							],
							"path": [
								"cachorros"
							]
						}
					},
					"response": []
				},
				{
					"name": "Editar Cachorro",
					"request": {
						"auth": {
							"type": "bearer",
							"bearer": [
								{
									"key": "token",
									"value": "eyJ0eXAiOiJKV1QiLCJhbGciOiJIUzI1NiJ9.eyJzdWIiOiIyIiwiaXNzIjoiUHJvZ3JhbWFTVEFSVEVSIiwiZXhwIjoxNjU5MDM1NzE5fQ.BUcnjzUcTuek60ReRsnKh0WioYu-uguzqnqBfg0SOtc",
									"type": "string"
								}
							]
						},
						"method": "PUT",
						"header": [],
						"body": {
							"mode": "raw",
							"raw": "{\r\n    \"nome\": \"Inui dog\",\r\n    \"racaId\": 10,\r\n    \"idade\": 5,\r\n    \"peso\": 21.3,\r\n    \"altura\": 14.6,\r\n    \"largura\": 6.1,\r\n    \"clienteId\" : 2\r\n}",
							"options": {
								"raw": {
									"language": "json"
								}
							}
						},
						"url": {
							"raw": "{{URL_API}}/cachorros/1",
							"host": [
								"{{URL_API}}"
							],
							"path": [
								"cachorros",
								"1"
							]
						}
					},
					"response": []
				},
				{
					"name": "Deletar Cachorro",
					"request": {
						"auth": {
							"type": "bearer",
							"bearer": [
								{
									"key": "token",
									"value": "eyJ0eXAiOiJKV1QiLCJhbGciOiJIUzI1NiJ9.eyJzdWIiOiIyIiwiaXNzIjoiUHJvZ3JhbWFTVEFSVEVSIiwiZXhwIjoxNjU5MDM1NzE5fQ.BUcnjzUcTuek60ReRsnKh0WioYu-uguzqnqBfg0SOtc",
									"type": "string"
								}
							]
						},
						"method": "DELETE",
						"header": [],
						"url": {
							"raw": "{{URL_API}}/cachorros/8",
							"host": [
								"{{URL_API}}"
							],
							"path": [
								"cachorros",
								"8"
							]
						}
					},
					"response": []
				}
			]
		},
		{
			"name": "Veterinario",
			"item": [
				{
					"name": "Buscar Veterinarios",
					"request": {
						"auth": {
							"type": "bearer",
							"bearer": [
								{
									"key": "token",
									"value": "eyJ0eXAiOiJKV1QiLCJhbGciOiJIUzI1NiJ9.eyJzdWIiOiIyIiwiaXNzIjoiUHJvZ3JhbWFTVEFSVEVSIiwiZXhwIjoxNjU5MDM1NzE5fQ.BUcnjzUcTuek60ReRsnKh0WioYu-uguzqnqBfg0SOtc",
									"type": "string"
								}
							]
						},
						"method": "GET",
						"header": [],
						"url": {
							"raw": "{{URL_API}}/veterinarios",
							"host": [
								"{{URL_API}}"
							],
							"path": [
								"veterinarios"
							]
						}
					},
					"response": []
				},
				{
					"name": "Buscar por ID",
					"request": {
						"auth": {
							"type": "bearer",
							"bearer": [
								{
									"key": "token",
									"value": "eyJ0eXAiOiJKV1QiLCJhbGciOiJIUzI1NiJ9.eyJzdWIiOiIyIiwiaXNzIjoiUHJvZ3JhbWFTVEFSVEVSIiwiZXhwIjoxNjU5MDM1NzE5fQ.BUcnjzUcTuek60ReRsnKh0WioYu-uguzqnqBfg0SOtc",
									"type": "string"
								}
							]
						},
						"method": "GET",
						"header": [],
						"url": {
							"raw": "{{URL_API}}/veterinarios/1",
							"host": [
								"{{URL_API}}"
							],
							"path": [
								"veterinarios",
								"1"
							]
						}
					},
					"response": []
				},
				{
					"name": "Salvar Veterinario",
					"request": {
						"auth": {
							"type": "bearer",
							"bearer": [
								{
									"key": "token",
									"value": "eyJ0eXAiOiJKV1QiLCJhbGciOiJIUzI1NiJ9.eyJzdWIiOiIyIiwiaXNzIjoiUHJvZ3JhbWFTVEFSVEVSIiwiZXhwIjoxNjU5MDM1NzE5fQ.BUcnjzUcTuek60ReRsnKh0WioYu-uguzqnqBfg0SOtc",
									"type": "string"
								}
							]
						},
						"method": "POST",
						"header": [],
						"body": {
							"mode": "raw",
							"raw": "{\r\n    \"nome\" : \"Veterinario\",\r\n    \"email\" : \"vet@gft.com\",\r\n    \"telefone\" : \"81999999999\",\r\n    \"num_registro\" : \"11111111111\",\r\n    \"endereco\" : {\r\n        \"logradouro\" : \"Rua B\",\r\n        \"numero\" : \"1234\",\r\n        \"complemento\" : \"\",\r\n        \"cep\" : \"11111111\"\r\n    }\r\n}",
							"options": {
								"raw": {
									"language": "json"
								}
							}
						},
						"url": {
							"raw": "{{URL_API}}/veterinarios",
							"host": [
								"{{URL_API}}"
							],
							"path": [
								"veterinarios"
							]
						}
					},
					"response": []
				},
				{
					"name": "Editar Veterinario",
					"request": {
						"auth": {
							"type": "bearer",
							"bearer": [
								{
									"key": "token",
									"value": "eyJ0eXAiOiJKV1QiLCJhbGciOiJIUzI1NiJ9.eyJzdWIiOiIyIiwiaXNzIjoiUHJvZ3JhbWFTVEFSVEVSIiwiZXhwIjoxNjU5MDM1NzE5fQ.BUcnjzUcTuek60ReRsnKh0WioYu-uguzqnqBfg0SOtc",
									"type": "string"
								}
							]
						},
						"method": "PUT",
						"header": [],
						"body": {
							"mode": "raw",
							"raw": "{\r\n    \"nome\" : \"Guilherme Atualizado\",\r\n    \"email\" : \"luiz@gft.com\",\r\n    \"telefone\" : \"81999999999\",\r\n    \"num_registro\" : \"11111111111\",\r\n    \"endereco\" : {\r\n        \"logradouro\" : \"Rua B\",\r\n        \"numero\" : \"1234\",\r\n        \"complemento\" : \"\",\r\n        \"cep\" : \"11111111\"\r\n    }\r\n}",
							"options": {
								"raw": {
									"language": "json"
								}
							}
						},
						"url": {
							"raw": "{{URL_API}}/veterinarios/1",
							"host": [
								"{{URL_API}}"
							],
							"path": [
								"veterinarios",
								"1"
							]
						}
					},
					"response": []
				},
				{
					"name": "Deletar Veterinario",
					"request": {
						"auth": {
							"type": "bearer",
							"bearer": [
								{
									"key": "token",
									"value": "eyJ0eXAiOiJKV1QiLCJhbGciOiJIUzI1NiJ9.eyJzdWIiOiIyIiwiaXNzIjoiUHJvZ3JhbWFTVEFSVEVSIiwiZXhwIjoxNjU5MDM1NzE5fQ.BUcnjzUcTuek60ReRsnKh0WioYu-uguzqnqBfg0SOtc",
									"type": "string"
								}
							]
						},
						"method": "DELETE",
						"header": [],
						"url": {
							"raw": "{{URL_API}}/veterinarios/2",
							"host": [
								"{{URL_API}}"
							],
							"path": [
								"veterinarios",
								"2"
							]
						}
					},
					"response": []
				}
			]
		},
		{
			"name": "Atendimento",
			"item": [
				{
					"name": "Buscar Atendimentos",
					"request": {
						"auth": {
							"type": "bearer",
							"bearer": [
								{
									"key": "token",
									"value": "eyJ0eXAiOiJKV1QiLCJhbGciOiJIUzI1NiJ9.eyJzdWIiOiIyIiwiaXNzIjoiUHJvZ3JhbWFTVEFSVEVSIiwiZXhwIjoxNjU5MDM1NzE5fQ.BUcnjzUcTuek60ReRsnKh0WioYu-uguzqnqBfg0SOtc",
									"type": "string"
								}
							]
						},
						"method": "GET",
						"header": [],
						"url": {
							"raw": "{{URL_API}}/atendimentos",
							"host": [
								"{{URL_API}}"
							],
							"path": [
								"atendimentos"
							]
						}
					},
					"response": []
				},
				{
					"name": "Buscar por ID",
					"request": {
						"auth": {
							"type": "bearer",
							"bearer": [
								{
									"key": "token",
									"value": "eyJ0eXAiOiJKV1QiLCJhbGciOiJIUzI1NiJ9.eyJzdWIiOiIyIiwiaXNzIjoiUHJvZ3JhbWFTVEFSVEVSIiwiZXhwIjoxNjU5MDM1NzE5fQ.BUcnjzUcTuek60ReRsnKh0WioYu-uguzqnqBfg0SOtc",
									"type": "string"
								}
							]
						},
						"method": "GET",
						"header": [],
						"url": {
							"raw": "{{URL_API}}/atendimentos/1",
							"host": [
								"{{URL_API}}"
							],
							"path": [
								"atendimentos",
								"1"
							]
						}
					},
					"response": []
				},
				{
					"name": "Salvar Atendimento",
					"request": {
						"auth": {
							"type": "bearer",
							"bearer": [
								{
									"key": "token",
									"value": "eyJ0eXAiOiJKV1QiLCJhbGciOiJIUzI1NiJ9.eyJzdWIiOiIyIiwiaXNzIjoiUHJvZ3JhbWFTVEFSVEVSIiwiZXhwIjoxNjU5MDM1NzE5fQ.BUcnjzUcTuek60ReRsnKh0WioYu-uguzqnqBfg0SOtc",
									"type": "string"
								}
							]
						},
						"method": "POST",
						"header": [],
						"body": {
							"mode": "raw",
							"raw": "{\r\n    \"data\" : \"22/07/2022\",\r\n    \"hora\" : \"12:00\",\r\n    \"idade_dia\" : 3,\r\n    \"peso_dia\" : 12.4,\r\n    \"altura_dia\" : 10.2,\r\n    \"largura_dia\" : 4.5,\r\n    \"diagnostico\" : \"Saúdavel\",\r\n    \"comentarios\" : \"Tudo ok\",\r\n    \"clienteId\" : 1,\r\n    \"veterinarioId\" : 1,\r\n    \"cachorroId\" : 1\r\n}",
							"options": {
								"raw": {
									"language": "json"
								}
							}
						},
						"url": {
							"raw": "{{URL_API}}/atendimentos",
							"host": [
								"{{URL_API}}"
							],
							"path": [
								"atendimentos"
							]
						}
					},
					"response": []
				},
				{
					"name": "Editar Atendimento",
					"request": {
						"auth": {
							"type": "bearer",
							"bearer": [
								{
									"key": "token",
									"value": "eyJ0eXAiOiJKV1QiLCJhbGciOiJIUzI1NiJ9.eyJzdWIiOiIyIiwiaXNzIjoiUHJvZ3JhbWFTVEFSVEVSIiwiZXhwIjoxNjU5MDM1NzE5fQ.BUcnjzUcTuek60ReRsnKh0WioYu-uguzqnqBfg0SOtc",
									"type": "string"
								}
							]
						},
						"method": "PUT",
						"header": [],
						"body": {
							"mode": "raw",
							"raw": "{\r\n    \"data\" : \"22/07/2022\",\r\n    \"hora\" : \"12:00\",\r\n    \"idade_dia\" : 3,\r\n    \"peso_dia\" : 12.4,\r\n    \"altura_dia\" : 10.2,\r\n    \"largura_dia\" : 4.5,\r\n    \"diagnostico\" : \"Saúdavel\",\r\n    \"comentarios\" : \"Tudo ok\",\r\n    \"clienteId\" : 1,\r\n    \"veterinarioId\" : 1,\r\n    \"cachorroId\" : 1\r\n}",
							"options": {
								"raw": {
									"language": "json"
								}
							}
						},
						"url": {
							"raw": "{{URL_API}}/atendimentos/2",
							"host": [
								"{{URL_API}}"
							],
							"path": [
								"atendimentos",
								"2"
							]
						}
					},
					"response": []
				},
				{
					"name": "Deletar Atendimento",
					"request": {
						"auth": {
							"type": "bearer",
							"bearer": [
								{
									"key": "token",
									"value": "eyJ0eXAiOiJKV1QiLCJhbGciOiJIUzI1NiJ9.eyJzdWIiOiIyIiwiaXNzIjoiUHJvZ3JhbWFTVEFSVEVSIiwiZXhwIjoxNjU5MDM1NzE5fQ.BUcnjzUcTuek60ReRsnKh0WioYu-uguzqnqBfg0SOtc",
									"type": "string"
								}
							]
						},
						"method": "DELETE",
						"header": [],
						"url": {
							"raw": "{{URL_API}}/atendimentos/2",
							"host": [
								"{{URL_API}}"
							],
							"path": [
								"atendimentos",
								"2"
							]
						}
					},
					"response": []
				}
			]
		},
		{
			"name": "Raça",
			"item": [
				{
					"name": "Listar Raças",
					"request": {
						"auth": {
							"type": "bearer",
							"bearer": [
								{
									"key": "token",
									"value": "eyJ0eXAiOiJKV1QiLCJhbGciOiJIUzI1NiJ9.eyJzdWIiOiIyIiwiaXNzIjoiUHJvZ3JhbWFTVEFSVEVSIiwiZXhwIjoxNjU5MDM1NzE5fQ.BUcnjzUcTuek60ReRsnKh0WioYu-uguzqnqBfg0SOtc",
									"type": "string"
								}
							]
						},
						"method": "GET",
						"header": [],
						"url": {
							"raw": "{{URL_API}}/racas",
							"host": [
								"{{URL_API}}"
							],
							"path": [
								"racas"
							]
						}
					},
					"response": []
				},
				{
					"name": "Filtar Raças",
					"protocolProfileBehavior": {
						"disableBodyPruning": true
					},
					"request": {
						"auth": {
							"type": "bearer",
							"bearer": [
								{
									"key": "token",
									"value": "eyJ0eXAiOiJKV1QiLCJhbGciOiJIUzI1NiJ9.eyJzdWIiOiIyIiwiaXNzIjoiUHJvZ3JhbWFTVEFSVEVSIiwiZXhwIjoxNjU5MDM1NzE5fQ.BUcnjzUcTuek60ReRsnKh0WioYu-uguzqnqBfg0SOtc",
									"type": "string"
								}
							]
						},
						"method": "GET",
						"header": [],
						"body": {
							"mode": "formdata",
							"formdata": [
								{
									"key": "",
									"type": "file",
									"src": []
								}
							]
						},
						"url": {
							"raw": "{{URL_API}}/racas/pesquisar?nome=golden",
							"host": [
								"{{URL_API}}"
							],
							"path": [
								"racas",
								"pesquisar"
							],
							"query": [
								{
									"key": "nome",
									"value": "golden"
								}
							]
						}
					},
					"response": []
				},
				{
					"name": "Buscar Raça por ID",
					"request": {
						"auth": {
							"type": "bearer",
							"bearer": [
								{
									"key": "token",
									"value": "eyJ0eXAiOiJKV1QiLCJhbGciOiJIUzI1NiJ9.eyJzdWIiOiIyIiwiaXNzIjoiUHJvZ3JhbWFTVEFSVEVSIiwiZXhwIjoxNjU5MDM1NzE5fQ.BUcnjzUcTuek60ReRsnKh0WioYu-uguzqnqBfg0SOtc",
									"type": "string"
								}
							]
						},
						"method": "GET",
						"header": [],
						"url": {
							"raw": "{{URL_API}}/racas/10",
							"host": [
								"{{URL_API}}"
							],
							"path": [
								"racas",
								"10"
							]
						}
					},
					"response": []
				}
			]
		},
		{
			"name": "Autenticar",
			"request": {
				"method": "POST",
				"header": [],
				"body": {
					"mode": "raw",
					"raw": "{\r\n    \"email\" : \"cliente@gft.com\",\r\n    \"senha\" : \"1234\"\r\n}",
					"options": {
						"raw": {
							"language": "json"
						}
					}
				},
				"url": {
					"raw": "{{URL_API}}/login",
					"host": [
						"{{URL_API}}"
					],
					"path": [
						"login"
					]
				}
			},
			"response": []
		},
		{
			"name": "Cadastrar Usuario",
			"request": {
				"method": "GET",
				"header": []
			},
			"response": []
		}
	]
}